py4mv/__init__.py
py4mv/helloworld.py
py4mv-0.0.1.dist-info/LICENSE.txt
py4mv-0.0.1.dist-info/METADATA
py4mv-0.0.1.dist-info/WHEEL
py4mv-0.0.1.dist-info/top_level.txt
py4mv-0.0.1.dist-info/RECORD
